odoo/addons/account_product_fiscal_classification/README.rst
odoo/addons/account_product_fiscal_classification/__init__.py
odoo/addons/account_product_fiscal_classification/__manifest__.py
odoo/addons/account_product_fiscal_classification/demo/account_product_fiscal_classification.xml
odoo/addons/account_product_fiscal_classification/demo/account_tax.xml
odoo/addons/account_product_fiscal_classification/demo/product_category.xml
odoo/addons/account_product_fiscal_classification/demo/product_template.xml
odoo/addons/account_product_fiscal_classification/demo/res_company.xml
odoo/addons/account_product_fiscal_classification/demo/res_groups.xml
odoo/addons/account_product_fiscal_classification/i18n/account_product_fiscal_classification.pot
odoo/addons/account_product_fiscal_classification/i18n/am.po
odoo/addons/account_product_fiscal_classification/i18n/ar.po
odoo/addons/account_product_fiscal_classification/i18n/bg.po
odoo/addons/account_product_fiscal_classification/i18n/bs.po
odoo/addons/account_product_fiscal_classification/i18n/ca.po
odoo/addons/account_product_fiscal_classification/i18n/ca_ES.po
odoo/addons/account_product_fiscal_classification/i18n/cs.po
odoo/addons/account_product_fiscal_classification/i18n/da.po
odoo/addons/account_product_fiscal_classification/i18n/de.po
odoo/addons/account_product_fiscal_classification/i18n/el_GR.po
odoo/addons/account_product_fiscal_classification/i18n/en_AU.po
odoo/addons/account_product_fiscal_classification/i18n/en_GB.po
odoo/addons/account_product_fiscal_classification/i18n/es.po
odoo/addons/account_product_fiscal_classification/i18n/es_AR.po
odoo/addons/account_product_fiscal_classification/i18n/es_CL.po
odoo/addons/account_product_fiscal_classification/i18n/es_CO.po
odoo/addons/account_product_fiscal_classification/i18n/es_CR.po
odoo/addons/account_product_fiscal_classification/i18n/es_DO.po
odoo/addons/account_product_fiscal_classification/i18n/es_EC.po
odoo/addons/account_product_fiscal_classification/i18n/es_ES.po
odoo12_addon_account_product_fiscal_classification-12.0.1.3.3.dist-info/METADATA
odoo12_addon_account_product_fiscal_classification-12.0.1.3.3.dist-info/WHEEL
odoo12_addon_account_product_fiscal_classification-12.0.1.3.3.dist-info/top_level.txt
odoo12_addon_account_product_fiscal_classification-12.0.1.3.3.dist-info/RECORD
