Metadata-Version: 2.1
Name: odoo12-addon-account-product-fiscal-classification
Version: 12.0.1.3.3
Summary: Simplify taxes management for products
Home-page: https://github.com/OCA/account-fiscal-rule
Author: Akretion,GRAP,La Louve,Odoo Community Association (OCA)
Author-email: support@odoo-community.org
License: AGPL-3
Platform: UNKNOWN
Classifier: Programming Language :: Python
Classifier: Framework :: Odoo
Classifier: Framework :: Odoo :: 12.0
Classifier: License :: OSI Approved :: GNU Affero General Public License v3
Requires-Python: >=3.5
Requires-Dist: odoo12-addon-account-coa-menu
Requires-Dist: odoo (<12.1dev,>=12.0a)
